bq_tabulate/__about__.py
bq_tabulate/__init__.py
bq_tabulate/tool.py
bq_tabulate-0.0.2.dist-info/METADATA
bq_tabulate-0.0.2.dist-info/WHEEL
bq_tabulate-0.0.2.dist-info/entry_points.txt
bq_tabulate-0.0.2.dist-info/licenses/LICENSE.txt
bq_tabulate-0.0.2.dist-info/RECORD
