Metadata-Version: 2.1
Name: bq-tabulate
Version: 0.0.2
Summary: A tool to format BQ results as tables
Project-URL: Documentation, https://github.com/logc/bq-tabulate#readme
Project-URL: Issues, https://github.com/logc/bq-tabulate/issues
Project-URL: Source, https://github.com/logc/bq-tabulate
Author-email: Luis Osa <luis.osa.gdc@gmail.com>
License-Expression: MIT
License-File: LICENSE.txt
Keywords: BigQuery,tabulate
Classifier: Development Status :: 4 - Beta
Classifier: Programming Language :: Python
Classifier: Programming Language :: Python :: 3.8
Classifier: Programming Language :: Python :: 3.9
Classifier: Programming Language :: Python :: 3.10
Classifier: Programming Language :: Python :: 3.11
Classifier: Programming Language :: Python :: Implementation :: CPython
Classifier: Programming Language :: Python :: Implementation :: PyPy
Requires-Python: >=3.8
Requires-Dist: tabulate
